meds_testing_helpers/__init__.py
meds_testing_helpers/dataset.py
meds_testing_helpers/dataset_generator.py
meds_testing_helpers/infer_dataset_config.py
meds_testing_helpers/pytest_plugin.py
meds_testing_helpers/rvs.py
meds_testing_helpers/types.py
meds_testing_helpers/configs/README.md
meds_testing_helpers/configs/generate_dataset.yaml
meds_testing_helpers/configs/infer_dataset_config.yaml
meds_testing_helpers/configs/dataset_spec/default.yaml
meds_testing_helpers/configs/dataset_spec/data_generator/default.yaml
meds_testing_helpers/configs/dataset_spec/data_generator/sample.yaml
meds_testing_helpers/static_sample_data/README.md
meds_testing_helpers/static_sample_data/__init__.py
meds_testing_helpers/static_sample_data/simple_static_sharded_by_split.yaml
meds_testing_helpers/static_sample_data/simple_static_sharded_by_split_with_tasks.yaml
meds_testing_helpers-0.3.1.dist-info/licenses/LICENSE
meds_testing_helpers-0.3.1.dist-info/METADATA
meds_testing_helpers-0.3.1.dist-info/WHEEL
meds_testing_helpers-0.3.1.dist-info/entry_points.txt
meds_testing_helpers-0.3.1.dist-info/top_level.txt
meds_testing_helpers-0.3.1.dist-info/RECORD
