Metadata-Version: 2.4
Name: meds_testing_helpers
Version: 0.3.1
Summary: Builds sample MEDS datasets for testing.
Author-email: Matthew McDermott <mattmcdermott8@gmail.com>
Project-URL: Homepage, https://meds-testing-helpers.readthedocs.io/en/latest/
Project-URL: Issues, https://github.com/Medical-Event-Data-Standard/meds_testing_helpers/issues
Classifier: Programming Language :: Python :: 3
Classifier: Framework :: Pytest
Classifier: License :: OSI Approved :: MIT License
Classifier: Operating System :: OS Independent
Requires-Python: >=3.10
License-File: LICENSE
Requires-Dist: annotated-types
Requires-Dist: numpy
Requires-Dist: hydra-core
Requires-Dist: polars
Requires-Dist: pytest
Requires-Dist: meds~=0.4.0
Requires-Dist: pyarrow
Requires-Dist: pytimeparse
Provides-Extra: dev
Requires-Dist: pre-commit<4; extra == "dev"
Requires-Dist: ruff; extra == "dev"
Provides-Extra: tests
Requires-Dist: pytest-cov; extra == "tests"
Provides-Extra: docs
Requires-Dist: mkdocs==1.6.1; extra == "docs"
Requires-Dist: mkdocs-material==9.6.7; extra == "docs"
Requires-Dist: mkdocstrings[python,shell]==0.28.2; extra == "docs"
Requires-Dist: mkdocs-gen-files==0.5.0; extra == "docs"
Requires-Dist: mkdocs-literate-nav==0.6.1; extra == "docs"
Requires-Dist: mkdocs-section-index==0.3.9; extra == "docs"
Requires-Dist: mkdocs-git-authors-plugin==0.9.2; extra == "docs"
Requires-Dist: mkdocs-git-revision-date-localized-plugin==1.3.0; extra == "docs"
Dynamic: license-file
